altmetrics/__init__.py
altmetrics/metrics.py
altmetrics-0.1.0.dist-info/licenses/LICENSE
altmetrics-0.1.0.dist-info/METADATA
altmetrics-0.1.0.dist-info/WHEEL
altmetrics-0.1.0.dist-info/top_level.txt
altmetrics-0.1.0.dist-info/RECORD
