Metadata-Version: 2.4
Name: altmetrics
Version: 0.1.0
Summary: Evaluate ASR and MT output with alternative-aware metrics.
Home-page: https://github.com/peregilk/altmetrics
Author: Per Kummervold
Author-email: Per Kummervold <Per.Kummervold@nb.no>
Project-URL: Homepage, https://github.com/peregilk/altmetrics
Project-URL: Repository, https://github.com/peregilk/altmetrics
Classifier: Programming Language :: Python :: 3
Classifier: License :: OSI Approved :: MIT License
Classifier: Operating System :: OS Independent
Requires-Python: >=3.8
License-File: LICENSE
Requires-Dist: jiwer>=2.0.0
Requires-Dist: sacrebleu>=2.4.0
Dynamic: author
Dynamic: home-page
Dynamic: license-file
Dynamic: requires-python
